genstates/__init__.py
genstates/exceptions.py
genstates-0.2.1.dist-info/LICENSE
genstates-0.2.1.dist-info/METADATA
genstates-0.2.1.dist-info/WHEEL
genstates-0.2.1.dist-info/RECORD
