Metadata-Version: 2.1
Name: genstates
Version: 0.2.1
Summary: 
Author: Jeffrey04
Author-email: mycyberpet@yahoo.com
Requires-Python: >=3.12,<4.0
Classifier: Programming Language :: Python :: 3
Classifier: Programming Language :: Python :: 3.12
Classifier: Programming Language :: Python :: 3.13
Requires-Dist: genruler (>=0.2.0,<0.3.0)
